codemd/__init__.py
codemd/cli.py
codemd/scanner.py
codemd-0.0.3.dist-info/METADATA
codemd-0.0.3.dist-info/WHEEL
codemd-0.0.3.dist-info/entry_points.txt
codemd-0.0.3.dist-info/licenses/LICENSE
codemd-0.0.3.dist-info/RECORD
