Metadata-Version: 2.3
Name: codemd
Version: 0.0.3
Summary: Transform code repositories into markdown-formatted strings ready for LLM prompting
Project-URL: Homepage, https://github.com/dotpyu/codemd
Project-URL: Bug Tracker, https://github.com/dotpyu/codemd/issues
Author-email: Peilin Yu <peilin_yu@brown.edu>
License: Apache-2.0
Classifier: License :: OSI Approved :: Apache Software License
Classifier: Operating System :: OS Independent
Classifier: Programming Language :: Python :: 3
Requires-Python: >=3.8
Requires-Dist: pathlib>=1.0.1
Requires-Dist: pathspec>=0.11.0
Requires-Dist: typing-extensions>=4.0.0
Provides-Extra: dev
Requires-Dist: black>=22.0; extra == 'dev'
Requires-Dist: flake8>=5.0; extra == 'dev'
Requires-Dist: mypy>=1.0; extra == 'dev'
Requires-Dist: pytest-cov>=4.0; extra == 'dev'
Requires-Dist: pytest>=7.0; extra == 'dev'
